runway/__init__.py
runway/settings.cpython-38-x86_64-linux-gnu.so
runway/cli/__init__.py
runway/cli/inference_server.py
runway/common/__init__.py
runway/common/api_client.cpython-38-x86_64-linux-gnu.so
runway/common/database.cpython-38-x86_64-linux-gnu.so
runway/common/enum_.cpython-38-x86_64-linux-gnu.so
runway/common/schemas.cpython-38-x86_64-linux-gnu.so
runway/common/utils.cpython-38-x86_64-linux-gnu.so
runway/common/values.cpython-38-x86_64-linux-gnu.so
runway/dataset/__init__.py
runway/dataset/api_client.cpython-38-x86_64-linux-gnu.so
runway/dataset/methods.cpython-38-x86_64-linux-gnu.so
runway/dataset/schemas.cpython-38-x86_64-linux-gnu.so
runway/dataset/values.cpython-38-x86_64-linux-gnu.so
runway/image_snapshot/__init__.py
runway/image_snapshot/api_client.cpython-38-x86_64-linux-gnu.so
runway/inference_services/__init__.py
runway/inference_services/api_client.cpython-38-x86_64-linux-gnu.so
runway/inference_services/methods.cpython-38-x86_64-linux-gnu.so
runway/inference_services/models.cpython-38-x86_64-linux-gnu.so
runway/inference_services/query_builders.cpython-38-x86_64-linux-gnu.so
runway/inference_services/schemas.cpython-38-x86_64-linux-gnu.so
runway/inference_services/values.cpython-38-x86_64-linux-gnu.so
runway/model_registry/__init__.py
runway/model_registry/api_client.cpython-38-x86_64-linux-gnu.so
runway/model_registry/schemas.cpython-38-x86_64-linux-gnu.so
runway/model_registry/values.cpython-38-x86_64-linux-gnu.so
runway/model_registry/methods/__init__.py
runway/model_registry/methods/common.cpython-38-x86_64-linux-gnu.so
runway/model_registry/methods/methods.cpython-38-x86_64-linux-gnu.so
runway/model_registry/methods/mlflow.cpython-38-x86_64-linux-gnu.so
runway/model_registry/methods/wandb.cpython-38-x86_64-linux-gnu.so
runway/model_registry/methods/artifacts/__init__.py
runway/model_registry/methods/artifacts/common.cpython-38-x86_64-linux-gnu.so
runway/model_registry/methods/artifacts/rev2/__init__.py
mrx_runway-1.13.3.dist-info/METADATA
mrx_runway-1.13.3.dist-info/WHEEL
mrx_runway-1.13.3.dist-info/top_level.txt
mrx_runway-1.13.3.dist-info/RECORD
